gen_pod_uq/__init__.py
gen_pod_uq/mc_pce_utils.py
gen_pod_uq-1.1.4.dist-info/AUTHORS
gen_pod_uq-1.1.4.dist-info/LICENSE
gen_pod_uq-1.1.4.dist-info/METADATA
gen_pod_uq-1.1.4.dist-info/WHEEL
gen_pod_uq-1.1.4.dist-info/pbr.json
gen_pod_uq-1.1.4.dist-info/top_level.txt
gen_pod_uq-1.1.4.dist-info/RECORD
