Metadata-Version: 2.1
Name: gen-pod-uq
Version: 1.1.4
Summary: Core module for genpod for UQ
Home-page: https://github.com/mpimd-csc/multidim-genpod-uq
Author: Jan Heiland
Author-email: jnhlnd@gmail.com
Maintainer: Jan Heiland
Maintainer-email: jnhlnd@gmail.com
License: MIT
Classifier: License :: OSI Approved :: MIT License
Classifier: Operating System :: OS Independent
Classifier: Programming Language :: Python
Classifier: Programming Language :: Python :: 3
License-File: LICENSE
License-File: AUTHORS
Requires-Dist: setuptools
Requires-Dist: pbr
Requires-Dist: rich
Requires-Dist: numpy
Requires-Dist: scipy
Requires-Dist: dolfin-navier-scipy (>=1.0.0)
Requires-Dist: sadptprj-riclyap-adi (>=1.0.0)
Requires-Dist: multidim-galerkin-pod (>=1.1.0)
